smartsheet_tools/__init__.py
smartsheet_tools-0.0.7.dist-info/licenses/LICENSE
smartsheet_tools-0.0.7.dist-info/METADATA
smartsheet_tools-0.0.7.dist-info/WHEEL
smartsheet_tools-0.0.7.dist-info/top_level.txt
smartsheet_tools-0.0.7.dist-info/RECORD
